samloc/__init__.py
samloc-0.0.1.dist-info/LICENSE
samloc-0.0.1.dist-info/METADATA
samloc-0.0.1.dist-info/WHEEL
samloc-0.0.1.dist-info/top_level.txt
samloc-0.0.1.dist-info/RECORD
