Metadata-Version: 2.1
Name: samloc
Version: 0.0.1
Summary: Sâm lốc
Home-page: 
Author: Pham Ngoc Minh
Author-email: phamngocminh1230@gmail.com
Classifier: Programming Language :: Python :: 3
Classifier: License :: OSI Approved :: MIT License
Classifier: Operating System :: OS Independent
License-File: LICENSE
